{"id":"A7EE5C6E-0DCC-4283-B0D8-9187E205DA45","validationEntity":{"analysedDataType":"auto","dataResult":{"createdDate":"2022-03-10T21:02:53Z"}},"modelEntity":{"createdDate":"2022-03-10T21:02:53Z","id":"CC484374-AD4E-4AC0-B1DD-E1A8CF1D9B71","experimentID":"A7EE5C6E-0DCC-4283-B0D8-9187E205DA45","title":"","modifiedDate":"2022-03-10T21:02:53Z","preferredFilename":"","version":"1.0","modelURL":"Models\/DistalRadiusClassifier%202.mlmodel"},"version":"1.0","settingEntity":{"taskType":"imageClassifier","augmentations":[],"styleTransferAlgorithmType":"image","iterationCount":25,"transferLearningEmbeddingType":"dynamic","harVideoAugmentations":0,"handPoseClassifierAugmentations":[],"algorithmType":"maxEnt","handActionClassifierAugmentations":[],"seedType":"default","featureNames":[]},"state":"trained","trainingEntity":{"finishTime":"2022-03-10T21:16:25Z","recipeTrainingResults":{"imageClassifier":{"confusionMatrix":[{"expected":"Acumed","actual":"Acumed","count":128},{"expected":"Arthrex","actual":"Acumed","count":2},{"expected":"Synthes","actual":"Acumed","count":1},{"expected":"Zimmer","actual":"Acumed","count":4},{"expected":"Arthrex","actual":"Arthrex","count":35},{"expected":"Skeletal Dynamics","actual":"Arthrex","count":1},{"expected":"Synthes","actual":"Arthrex","count":1},{"expected":"Trimed","actual":"Arthrex","count":1},{"expected":"Skeletal Dynamics","actual":"Skeletal Dynamics","count":86},{"expected":"Synthes","actual":"Skeletal Dynamics","count":2},{"expected":"Acumed","actual":"Synthes","count":4},{"expected":"Arthrex","actual":"Synthes","count":1},{"expected":"Synthes","actual":"Synthes","count":228},{"expected":"Trimed","actual":"Synthes","count":1},{"expected":"Acumed","actual":"Trimed","count":2},{"expected":"Skeletal Dynamics","actual":"Trimed","count":1},{"expected":"Trimed","actual":"Trimed","count":72},{"expected":"Acumed","actual":"Zimmer","count":2},{"expected":"Synthes","actual":"Zimmer","count":1},{"expected":"Trimed","actual":"Zimmer","count":1},{"expected":"Zimmer","actual":"Zimmer","count":57}],"statsByLabel":{"Skeletal Dynamics":{"count":88,"precisionRecall":{"success":{"recall":0.97727272727272729,"precision":0.97727272727272729}}},"Trimed":{"count":75,"precisionRecall":{"success":{"recall":0.95999999999999996,"precision":0.95999999999999996}}},"Zimmer":{"count":61,"precisionRecall":{"success":{"recall":0.93442622950819676,"precision":0.93442622950819676}}},"Arthrex":{"count":38,"precisionRecall":{"success":{"recall":0.92105263157894735,"precision":0.92105263157894735}}},"Synthes":{"count":234,"precisionRecall":{"success":{"recall":0.97435897435897434,"precision":0.97854077253218885}}},"Acumed":{"count":135,"precisionRecall":{"success":{"recall":0.94814814814814818,"precision":0.94117647058823528}}}},"accuracy":0.96038034865293187}},"dataResult":{"itemsCount":670,"createdDate":"2022-03-10T21:02:53Z","dataURL":"file:\/\/\/Users\/dylanmace\/Downloads\/distal-radius-implant-identifier-17fefc814f5416765e645928f650aab5aeb48718\/ML\/images\/","dataSourceID":"E5B1B97E-CEC1-4613-81B2-4BD1C41AA4B6","classesCount":6,"analysis":{"summary":{"canUseValidation":1,"classCount":6,"sampleCount":670},"issues":[{"description":"6 classes found, including Synthes, Acumed, Skeletal Dynamics","severity":"debug"},{"description":"670 images found, automatically creating validation set","severity":"good"},{"description":"Smallest class is \"Arthrex\" with 41 images","severity":"debug"},{"description":"Largest class is \"Synthes\" with 245 images","severity":"debug"}],"classifierAnalysis":{"labelStats":{"Arthrex":41,"Trimed":80,"Zimmer":62,"Acumed":147,"Synthes":245,"Skeletal Dynamics":95}}}},"dataURL":"file:\/\/\/Users\/dylanmace\/Downloads\/distal-radius-implant-identifier-17fefc814f5416765e645928f650aab5aeb48718\/ML\/images\/","featureExtractionCheckpointMayBeAvailable":false,"recipeValidationResults":{"imageClassifier":{"confusionMatrix":[{"expected":"Acumed","actual":"Acumed","count":9},{"expected":"Synthes","actual":"Acumed","count":2},{"expected":"Zimmer","actual":"Acumed","count":1},{"expected":"Acumed","actual":"Arthrex","count":1},{"expected":"Arthrex","actual":"Arthrex","count":1},{"expected":"Trimed","actual":"Arthrex","count":1},{"expected":"Acumed","actual":"Skeletal Dynamics","count":2},{"expected":"Skeletal Dynamics","actual":"Skeletal Dynamics","count":4},{"expected":"Trimed","actual":"Skeletal Dynamics","count":1},{"expected":"Synthes","actual":"Synthes","count":11},{"expected":"Synthes","actual":"Trimed","count":2},{"expected":"Trimed","actual":"Trimed","count":3},{"expected":"Trimed","actual":"Zimmer","count":1}],"statsByLabel":{"Arthrex":{"count":3,"precisionRecall":{"success":{"recall":0.33333333333333331,"precision":1}}},"Trimed":{"count":5,"precisionRecall":{"success":{"recall":0.59999999999999998,"precision":0.5}}},"Zimmer":{"count":1,"precisionRecall":{"success":{"recall":0,"precision":0}}},"Acumed":{"count":12,"precisionRecall":{"success":{"recall":0.75,"precision":0.75}}},"Synthes":{"count":11,"precisionRecall":{"success":{"recall":1,"precision":0.73333333333333328}}},"Skeletal Dynamics":{"count":7,"precisionRecall":{"success":{"recall":0.5714285714285714,"precision":1}}}},"accuracy":0.71794871794871795}},"progress":[{"currentRowIndex":0,"tableIndex":0,"count":0,"isLast":false,"percentComplete":0,"tableDone":false},{"icTrainingColumnHeader":{"hasValidation":true,"elapsedTime":1.0623689999999999,"trainingAccuracy":0.37084,"iterationCount":1,"validationAccuracy":0.282051},"isLast":false,"currentRowIndex":0,"count":1,"tableDone":false,"tableIndex":67,"percentComplete":0},{"icTrainingColumnHeader":{"hasValidation":true,"elapsedTime":1.121942,"trainingAccuracy":0.37084,"iterationCount":2,"validationAccuracy":0.282051},"isLast":false,"currentRowIndex":0,"count":2,"tableDone":false,"tableIndex":67,"percentComplete":0},{"icTrainingColumnHeader":{"hasValidation":true,"elapsedTime":1.144655,"trainingAccuracy":0.38985700000000001,"iterationCount":3,"validationAccuracy":0.30769200000000002},"isLast":false,"currentRowIndex":0,"count":3,"tableDone":false,"tableIndex":67,"percentComplete":0},{"icTrainingColumnHeader":{"hasValidation":true,"elapsedTime":1.164134,"trainingAccuracy":0.44374000000000002,"iterationCount":4,"validationAccuracy":0.38461499999999998},"isLast":false,"currentRowIndex":0,"count":4,"tableDone":false,"tableIndex":67,"percentComplete":0},{"icTrainingColumnHeader":{"hasValidation":true,"elapsedTime":1.2009799999999999,"trainingAccuracy":0.462758,"iterationCount":5,"validationAccuracy":0.41025600000000001},"isLast":false,"currentRowIndex":0,"count":5,"tableDone":false,"tableIndex":67,"percentComplete":0},{"icTrainingColumnHeader":{"hasValidation":true,"elapsedTime":1.3447519999999999,"trainingAccuracy":0.65927100000000005,"iterationCount":10,"validationAccuracy":0.461538},"isLast":false,"currentRowIndex":0,"count":10,"tableDone":false,"tableIndex":67,"percentComplete":0},{"currentRowIndex":0,"tableIndex":0,"count":20,"isLast":false,"percentComplete":0,"tableDone":false},{"icTrainingColumnHeader":{"hasValidation":true,"elapsedTime":1.689084,"trainingAccuracy":0.96038000000000001,"iterationCount":25,"validationAccuracy":0.71794899999999995},"isLast":false,"currentRowIndex":0,"count":25,"tableDone":true,"tableIndex":67,"percentComplete":0},{"currentRowIndex":0,"tableIndex":0,"count":30,"isLast":false,"percentComplete":0,"tableDone":false},{"currentRowIndex":0,"tableIndex":0,"count":40,"isLast":false,"percentComplete":0,"tableDone":false},{"currentRowIndex":0,"tableIndex":0,"count":50,"isLast":false,"percentComplete":0,"tableDone":false},{"currentRowIndex":0,"tableIndex":0,"count":60,"isLast":false,"percentComplete":0,"tableDone":false},{"currentRowIndex":0,"tableIndex":0,"count":70,"isLast":false,"percentComplete":0,"tableDone":false},{"currentRowIndex":0,"tableIndex":0,"count":80,"isLast":false,"percentComplete":0,"tableDone":false},{"currentRowIndex":0,"tableIndex":0,"count":90,"isLast":false,"percentComplete":0,"tableDone":false},{"currentRowIndex":0,"tableIndex":0,"count":100,"isLast":false,"percentComplete":0,"tableDone":false},{"currentRowIndex":0,"tableIndex":0,"count":110,"isLast":false,"percentComplete":0,"tableDone":false},{"currentRowIndex":0,"tableIndex":0,"count":120,"isLast":false,"percentComplete":0,"tableDone":false},{"currentRowIndex":0,"tableIndex":0,"count":130,"isLast":false,"percentComplete":0,"tableDone":false},{"currentRowIndex":0,"tableIndex":0,"count":140,"isLast":false,"percentComplete":0,"tableDone":false},{"currentRowIndex":0,"tableIndex":0,"count":150,"isLast":false,"percentComplete":0,"tableDone":false},{"currentRowIndex":0,"tableIndex":0,"count":160,"isLast":false,"percentComplete":0,"tableDone":false},{"currentRowIndex":0,"tableIndex":0,"count":170,"isLast":false,"percentComplete":0,"tableDone":false},{"currentRowIndex":0,"tableIndex":0,"count":180,"isLast":false,"percentComplete":0,"tableDone":false},{"currentRowIndex":0,"tableIndex":0,"count":190,"isLast":false,"percentComplete":0,"tableDone":false},{"currentRowIndex":0,"tableIndex":0,"count":200,"isLast":false,"percentComplete":0,"tableDone":false},{"currentRowIndex":0,"tableIndex":0,"count":210,"isLast":false,"percentComplete":0,"tableDone":false},{"currentRowIndex":0,"tableIndex":0,"count":220,"isLast":false,"percentComplete":0,"tableDone":false},{"currentRowIndex":0,"tableIndex":0,"count":230,"isLast":false,"percentComplete":0,"tableDone":false},{"currentRowIndex":0,"tableIndex":0,"count":240,"isLast":false,"percentComplete":0,"tableDone":false},{"currentRowIndex":0,"tableIndex":0,"count":250,"isLast":false,"percentComplete":0,"tableDone":false},{"currentRowIndex":0,"tableIndex":0,"count":260,"isLast":false,"percentComplete":0,"tableDone":false},{"currentRowIndex":0,"tableIndex":0,"count":270,"isLast":false,"percentComplete":0,"tableDone":false},{"currentRowIndex":0,"tableIndex":0,"count":280,"isLast":false,"percentComplete":0,"tableDone":false},{"currentRowIndex":0,"tableIndex":0,"count":290,"isLast":false,"percentComplete":0,"tableDone":false},{"currentRowIndex":0,"tableIndex":0,"count":300,"isLast":false,"percentComplete":0,"tableDone":false},{"currentRowIndex":0,"tableIndex":0,"count":310,"isLast":false,"percentComplete":0,"tableDone":false},{"currentRowIndex":0,"tableIndex":0,"count":320,"isLast":false,"percentComplete":0,"tableDone":false},{"currentRowIndex":0,"tableIndex":0,"count":330,"isLast":false,"percentComplete":0,"tableDone":false},{"currentRowIndex":0,"tableIndex":0,"count":340,"isLast":false,"percentComplete":0,"tableDone":false},{"currentRowIndex":0,"tableIndex":0,"count":350,"isLast":false,"percentComplete":0,"tableDone":false},{"currentRowIndex":0,"tableIndex":0,"count":360,"isLast":false,"percentComplete":0,"tableDone":false},{"currentRowIndex":0,"tableIndex":0,"count":370,"isLast":false,"percentComplete":0,"tableDone":false},{"currentRowIndex":0,"tableIndex":0,"count":380,"isLast":false,"percentComplete":0,"tableDone":false},{"currentRowIndex":0,"tableIndex":0,"count":390,"isLast":false,"percentComplete":0,"tableDone":false},{"currentRowIndex":0,"tableIndex":0,"count":400,"isLast":false,"percentComplete":0,"tableDone":false},{"currentRowIndex":0,"tableIndex":0,"count":410,"isLast":false,"percentComplete":0,"tableDone":false},{"currentRowIndex":0,"tableIndex":0,"count":420,"isLast":false,"percentComplete":0,"tableDone":false},{"currentRowIndex":0,"tableIndex":0,"count":430,"isLast":false,"percentComplete":0,"tableDone":false},{"currentRowIndex":0,"tableIndex":0,"count":440,"isLast":false,"percentComplete":0,"tableDone":false},{"currentRowIndex":0,"tableIndex":0,"count":450,"isLast":false,"percentComplete":0,"tableDone":false},{"currentRowIndex":0,"tableIndex":0,"count":460,"isLast":false,"percentComplete":0,"tableDone":false},{"currentRowIndex":0,"tableIndex":0,"count":470,"isLast":false,"percentComplete":0,"tableDone":false},{"currentRowIndex":0,"tableIndex":0,"count":480,"isLast":false,"percentComplete":0,"tableDone":false},{"currentRowIndex":0,"tableIndex":0,"count":490,"isLast":false,"percentComplete":0,"tableDone":false},{"currentRowIndex":0,"tableIndex":0,"count":500,"isLast":false,"percentComplete":0,"tableDone":false},{"currentRowIndex":0,"tableIndex":0,"count":510,"isLast":false,"percentComplete":0,"tableDone":false},{"currentRowIndex":0,"tableIndex":0,"count":520,"isLast":false,"percentComplete":0,"tableDone":false},{"currentRowIndex":0,"tableIndex":0,"count":530,"isLast":false,"percentComplete":0,"tableDone":false},{"currentRowIndex":0,"tableIndex":0,"count":540,"isLast":false,"percentComplete":0,"tableDone":false},{"currentRowIndex":0,"tableIndex":0,"count":550,"isLast":false,"percentComplete":0,"tableDone":false},{"currentRowIndex":0,"tableIndex":0,"count":560,"isLast":false,"percentComplete":0,"tableDone":false},{"currentRowIndex":0,"tableIndex":0,"count":570,"isLast":false,"percentComplete":0,"tableDone":false},{"currentRowIndex":0,"tableIndex":0,"count":580,"isLast":false,"percentComplete":0,"tableDone":false},{"currentRowIndex":0,"tableIndex":0,"count":590,"isLast":false,"percentComplete":0,"tableDone":false},{"currentRowIndex":0,"tableIndex":0,"count":600,"isLast":false,"percentComplete":0,"tableDone":false},{"currentRowIndex":0,"tableIndex":0,"count":610,"isLast":false,"percentComplete":0,"tableDone":false},{"currentRowIndex":0,"tableIndex":0,"count":620,"isLast":false,"percentComplete":0,"tableDone":false},{"currentRowIndex":0,"tableIndex":0,"count":630,"isLast":false,"percentComplete":0,"tableDone":false},{"currentRowIndex":0,"tableIndex":0,"count":640,"isLast":false,"percentComplete":0,"tableDone":false},{"currentRowIndex":0,"tableIndex":0,"count":650,"isLast":false,"percentComplete":0,"tableDone":false},{"currentRowIndex":0,"tableIndex":0,"count":660,"isLast":false,"percentComplete":0,"tableDone":false},{"currentRowIndex":0,"tableIndex":0,"count":670,"isLast":false,"percentComplete":0,"tableDone":true}],"trainingAccuracy":0.96038034865293187,"checkpointMetrics":{},"analysedDataType":"none","dataSourceID":"E5B1B97E-CEC1-4613-81B2-4BD1C41AA4B6","snapshottableCheckpoints":{},"validationAccuracy":0.71794871794871795,"startTime":"2022-03-10T21:16:13Z"},"createdDate":"2022-03-10T21:02:53Z","evaluationContainerEntity":{"testingEvaluationEntity":{"id":"d59dc88d-fe25-4fe5-8f6d-22607a2ee1df","createdDate":"2022-03-10T21:02:53Z","dataResult":{"createdDate":"2022-03-10T21:02:53Z"},"analysedDataType":"none"},"createdDate":"2022-03-10T22:12:54Z","id":"a17ba69a-6147-4c60-a15c-ee0c5f497a83","trainingEvaluationEntity":{"result":{"imageClassifier":{"confusionMatrix":[{"expected":"Acumed","actual":"Acumed","count":128},{"expected":"Arthrex","actual":"Acumed","count":2},{"expected":"Synthes","actual":"Acumed","count":1},{"expected":"Zimmer","actual":"Acumed","count":4},{"expected":"Arthrex","actual":"Arthrex","count":35},{"expected":"Skeletal Dynamics","actual":"Arthrex","count":1},{"expected":"Synthes","actual":"Arthrex","count":1},{"expected":"Trimed","actual":"Arthrex","count":1},{"expected":"Skeletal Dynamics","actual":"Skeletal Dynamics","count":86},{"expected":"Synthes","actual":"Skeletal Dynamics","count":2},{"expected":"Acumed","actual":"Synthes","count":4},{"expected":"Arthrex","actual":"Synthes","count":1},{"expected":"Synthes","actual":"Synthes","count":228},{"expected":"Trimed","actual":"Synthes","count":1},{"expected":"Acumed","actual":"Trimed","count":2},{"expected":"Skeletal Dynamics","actual":"Trimed","count":1},{"expected":"Trimed","actual":"Trimed","count":72},{"expected":"Acumed","actual":"Zimmer","count":2},{"expected":"Synthes","actual":"Zimmer","count":1},{"expected":"Trimed","actual":"Zimmer","count":1},{"expected":"Zimmer","actual":"Zimmer","count":57}],"statsByLabel":{"Skeletal Dynamics":{"count":88,"precisionRecall":{"success":{"recall":0.97727272727272729,"precision":0.97727272727272729}}},"Trimed":{"count":75,"precisionRecall":{"success":{"recall":0.95999999999999996,"precision":0.95999999999999996}}},"Zimmer":{"count":61,"precisionRecall":{"success":{"recall":0.93442622950819676,"precision":0.93442622950819676}}},"Arthrex":{"count":38,"precisionRecall":{"success":{"recall":0.92105263157894735,"precision":0.92105263157894735}}},"Synthes":{"count":234,"precisionRecall":{"success":{"recall":0.97435897435897434,"precision":0.97854077253218885}}},"Acumed":{"count":135,"precisionRecall":{"success":{"recall":0.94814814814814818,"precision":0.94117647058823528}}}},"accuracy":0.96038034865293187}},"createdDate":"2022-03-10T21:02:53Z","id":"71f461d9-7a61-4d17-8c6a-bbeb9eb5f989","dataURL":"file:\/\/\/Users\/dylanmace\/Downloads\/distal-radius-implant-identifier-17fefc814f5416765e645928f650aab5aeb48718\/ML\/images\/","dataSourceID":"E5B1B97E-CEC1-4613-81B2-4BD1C41AA4B6","dataResult":{"itemsCount":670,"createdDate":"2022-03-10T21:02:53Z","dataURL":"file:\/\/\/Users\/dylanmace\/Downloads\/distal-radius-implant-identifier-17fefc814f5416765e645928f650aab5aeb48718\/ML\/images\/","dataSourceID":"E5B1B97E-CEC1-4613-81B2-4BD1C41AA4B6","classesCount":6,"analysis":{"summary":{"canUseValidation":1,"classCount":6,"sampleCount":670},"issues":[{"description":"6 classes found, including Synthes, Acumed, Skeletal Dynamics","severity":"debug"},{"description":"670 images found, automatically creating validation set","severity":"good"},{"description":"Smallest class is \"Arthrex\" with 41 images","severity":"debug"},{"description":"Largest class is \"Synthes\" with 245 images","severity":"debug"}],"classifierAnalysis":{"labelStats":{"Arthrex":41,"Trimed":80,"Zimmer":62,"Acumed":147,"Synthes":245,"Skeletal Dynamics":95}}}},"analysedDataType":"none"},"previewType":"imageClassifier","modifiedDate":"2022-03-10T22:12:54Z","validationEvaluationEntity":{"result":{"imageClassifier":{"confusionMatrix":[{"expected":"Acumed","actual":"Acumed","count":9},{"expected":"Synthes","actual":"Acumed","count":2},{"expected":"Zimmer","actual":"Acumed","count":1},{"expected":"Acumed","actual":"Arthrex","count":1},{"expected":"Arthrex","actual":"Arthrex","count":1},{"expected":"Trimed","actual":"Arthrex","count":1},{"expected":"Acumed","actual":"Skeletal Dynamics","count":2},{"expected":"Skeletal Dynamics","actual":"Skeletal Dynamics","count":4},{"expected":"Trimed","actual":"Skeletal Dynamics","count":1},{"expected":"Synthes","actual":"Synthes","count":11},{"expected":"Synthes","actual":"Trimed","count":2},{"expected":"Trimed","actual":"Trimed","count":3},{"expected":"Trimed","actual":"Zimmer","count":1}],"statsByLabel":{"Arthrex":{"count":3,"precisionRecall":{"success":{"recall":0.33333333333333331,"precision":1}}},"Trimed":{"count":5,"precisionRecall":{"success":{"recall":0.59999999999999998,"precision":0.5}}},"Zimmer":{"count":1,"precisionRecall":{"success":{"recall":0,"precision":0}}},"Acumed":{"count":12,"precisionRecall":{"success":{"recall":0.75,"precision":0.75}}},"Synthes":{"count":11,"precisionRecall":{"success":{"recall":1,"precision":0.73333333333333328}}},"Skeletal Dynamics":{"count":7,"precisionRecall":{"success":{"recall":0.5714285714285714,"precision":1}}}},"accuracy":0.71794871794871795}},"id":"14e78b5b-5967-4ee8-b6c2-789770a13fd9","createdDate":"2022-03-10T21:02:53Z","dataResult":{"createdDate":"2022-03-10T21:02:53Z"},"analysedDataType":"auto"},"evaluationEntities":[{"id":"55204db3-d854-4923-b7a3-d691ae592207","createdDate":"2022-03-10T21:19:10Z","dataResult":{"createdDate":"2022-03-10T21:19:32Z"},"analysedDataType":"none"}]},"evaluationEntities":[],"activityEntities":["experimentCreated",[{"id":"EA5B7524-C801-4387-9821-1E798C82DABE","title":"Model Source Created","createdDate":"2022-03-10T21:02:53Z","event":"experimentCreated","subtitle":"DistalRadiusClassifier 2"}],"trainingFinished",[{"id":"B2C39160-84C0-4F22-BBC8-79CF31894773","title":"Training Completed","createdDate":"2022-03-10T21:16:25Z","event":"trainingFinished","subtitle":"25 iterations"}],"trainingDataAdded",[{"id":"F8F2D931-4C8F-423B-9872-21C791B0413D","title":"Training Data Added","createdDate":"2022-03-10T21:16:04Z","event":"trainingDataAdded","subtitle":"images"}],"trainingStarted",[{"id":"E9A3B790-1AF2-4447-B437-70285E336A53","title":"Training Started","createdDate":"2022-03-10T21:16:13Z","event":"trainingStarted","subtitle":"25 iterations"}]],"title":"DistalRadiusClassifier 2","evaluationEntity":{"id":"7a7b4632-fd44-4ce8-a988-77cd7c6a683d","createdDate":"2022-03-10T21:02:53Z","dataResult":{"createdDate":"2022-03-10T21:02:53Z"},"analysedDataType":"none"},"evaluationState":"uninitialized","snapshotRole":{"withoutSnapshots":0},"modifiedDate":"2022-03-10T22:12:54Z","contentDataResult":{"createdDate":"2022-03-10T21:02:53Z"},"preferredFilename":"DistalRadiusClassifier 2"}